functorflow.cpython-37m-x86_64-linux-gnu.so
setup.py
functorflow-2.2.5.dist-info/METADATA
functorflow-2.2.5.dist-info/WHEEL
functorflow-2.2.5.dist-info/top_level.txt
functorflow-2.2.5.dist-info/RECORD
